cryptopals/__init__.py
cryptopals/attacks/__init__.py
cryptopals/attacks/aes.py
cryptopals/attacks/xor.py
cryptopals/building_blocks/__init__.py
cryptopals/building_blocks/aes.py
cryptopals/building_blocks/base64.py
cryptopals/building_blocks/input_output.py
cryptopals/building_blocks/statistics.py
cryptopals/building_blocks/xor.py
cryptopals-0.1.0.dist-info/METADATA
cryptopals-0.1.0.dist-info/WHEEL
cryptopals-0.1.0.dist-info/top_level.txt
cryptopals-0.1.0.dist-info/RECORD
