Metadata-Version: 2.1
Name: cryptopals
Version: 0.1.0
Summary: Provides building blocks that can be used to complete Matasano Cryptopals Challenges
Home-page: https://github.com/kmanc/cryptopals
Author: Kevin Conley
Author-email: kmancxc@gmail.com
License: MIT
Keywords: Python,Crypto,Cryptopals
Platform: UNKNOWN
Classifier: Development Status :: 5 - Production/Stable
Classifier: Topic :: Utilities
Requires-Python: >=3.6
